CHANGES.rst
LICENSE
MANIFEST.in
README.rst
schunk.py
setup.py
SchunkMotionProtocol.egg-info/PKG-INFO
SchunkMotionProtocol.egg-info/SOURCES.txt
SchunkMotionProtocol.egg-info/dependency_links.txt
SchunkMotionProtocol.egg-info/top_level.txt
doc/Makefile
doc/conf.py
doc/index.rst
doc/make.bat
doc/requirements.txt
test/test_dummyconnection.py
test/test_interrupt_blocking.py
test/test_wait.py