Metadata-Version: 1.1
Name: SchunkMotionProtocol
Version: 0.2.2
Summary: Schunk Motion Protocol for Python
Home-page: http://schunk.rtfd.org/
Author: Matthias Geier
Author-email: Matthias.Geier@gmail.com
License: MIT
Download-URL: https://github.com/spatialaudio/schunk/releases/
Keywords: Schunk,serial,servo,motor
Platform: any
Classifier: Development Status :: 3 - Alpha
Classifier: License :: OSI Approved :: MIT License
Classifier: Operating System :: OS Independent
Classifier: Programming Language :: Python
Classifier: Programming Language :: Python :: 2
Classifier: Programming Language :: Python :: 3
Classifier: Topic :: Scientific/Engineering
